XObject_GlobalData-3.1.3.dist-info/DESCRIPTION.rst
XObject_GlobalData-3.1.3.dist-info/METADATA
XObject_GlobalData-3.1.3.dist-info/RECORD
XObject_GlobalData-3.1.3.dist-info/WHEEL
XObject_GlobalData-3.1.3.dist-info/metadata.json
XObject_GlobalData-3.1.3.dist-info/top_level.txt
xo/__init__.py
xo/fileWatch.py
xo/gd.py
xo/osCommands.py
xo/sync.py
xo/xo.py
xo/xoHelper.py
