Metadata-Version: 2.0
Name: XObject-GlobalData
Version: 3.1.3
Summary: Use Python Like You Never Have Before, Easy Acces To: Events and Triggers, Realtime MultiProcessing, Instant Dynamic DB, Filesytem & Web Watchdog, Sockets, API Server, Support You Fast Prototyping To Large Scale Systems
Home-page: https://github.com/fire17/xo-gd
Author: Tami Bar
Author-email: fire17@gmail.com
License: BSD
Download-URL: https://github.com/fire17/xo-gd/tarball/3.1.3
Platform: UNKNOWN
Classifier: Development Status :: 3 - Alpha
Classifier: Intended Audience :: Developers
Classifier: Programming Language :: Python :: 3
Requires-Dist: GitPython
Requires-Dist: dill
Requires-Dist: psutil (==5.4.2)
Requires-Dist: traceback
